[
  {
    "name": "Nature of the Beast",
    "commander": "Marath, Will of the Wild",
    "expansion": "Commander 2013",
    "cards": [
      {
        "name": "Archangel",
        "count": 1
      },
      {
        "name": "Avenger of Zendikar",
        "count": 1
      },
      {
        "name": "Baloth Woodcrasher",
        "count": 1
      },
      {
        "name": "Crater Hellion",
        "count": 1
      },
      {
        "name": "Deadwood Treefolk",
        "count": 1
      },
      {
        "name": "Drumhunter",
        "count": 1
      },
      {
        "name": "Eternal Dragon",
        "count": 1
      },
      {
        "name": "Gahiji, Honored One",
        "count": 1
      },
      {
        "name": "Grazing Gladehart",
        "count": 1
      },
      {
        "name": "Krosan Tusker",
        "count": 1
      },
      {
        "name": "Krosan Warchief",
        "count": 1
      },
      {
        "name": "Magus of the Arena",
        "count": 1
      },
      {
        "name": "Mayael the Anima",
        "count": 1
      },
      {
        "name": "Mold Shambler",
        "count": 1
      },
      {
        "name": "Naya Soulbeast",
        "count": 1
      },
      {
        "name": "Rakeclaw Gargantuan",
        "count": 1
      },
      {
        "name": "Rampaging Baloths",
        "count": 1
      },
      {
        "name": "Ravenous Baloth",
        "count": 1
      },
      {
        "name": "Spellbreaker Behemoth",
        "count": 1
      },
      {
        "name": "Spitebellows",
        "count": 1
      },
      {
        "name": "Terra Ravager",
        "count": 1
      },
      {
        "name": "Valley Rannet",
        "count": 1
      },
      {
        "name": "Cultivate",
        "count": 1
      },
      {
        "name": "Fiery Justice",
        "count": 1
      },
      {
        "name": "Fireball",
        "count": 1
      },
      {
        "name": "From the Ashes",
        "count": 1
      },
      {
        "name": "Harmonize",
        "count": 1
      },
      {
        "name": "Hull Breach",
        "count": 1
      },
      {
        "name": "One Dozen Eyes",
        "count": 1
      },
      {
        "name": "Rain of Thorns",
        "count": 1
      },
      {
        "name": "Restore",
        "count": 1
      },
      {
        "name": "Savage Twister",
        "count": 1
      },
      {
        "name": "Slice and Dice",
        "count": 1
      },
      {
        "name": "Tempt with Discovery",
        "count": 1
      },
      {
        "name": "Wrath of God",
        "count": 1
      },
      {
        "name": "Boros Charm",
        "count": 1
      },
      {
        "name": "Naya Charm",
        "count": 1
      },
      {
        "name": "Slice in Twain",
        "count": 1
      },
      {
        "name": "Sprouting Vines",
        "count": 1
      },
      {
        "name": "Street Spasm",
        "count": 1
      },
      {
        "name": "Behemoth Sledge",
        "count": 1
      },
      {
        "name": "Druidic Satchel",
        "count": 1
      },
      {
        "name": "Seer's Sundial",
        "count": 1
      },
      {
        "name": "Sol Ring",
        "count": 1
      },
      {
        "name": "Swiftfoot Boots",
        "count": 1
      },
      {
        "name": "Tower of Fortunes",
        "count": 1
      },
      {
        "name": "Curse of Chaos",
        "count": 1
      },
      {
        "name": "Curse of Predation",
        "count": 1
      },
      {
        "name": "Curse of the Forsaken",
        "count": 1
      },
      {
        "name": "Darksteel Mutation",
        "count": 1
      },
      {
        "name": "Fires of Yavimaya",
        "count": 1
      },
      {
        "name": "Mystic Barrier",
        "count": 1
      },
      {
        "name": "Spawning Grounds",
        "count": 1
      },
      {
        "name": "War Cadence",
        "count": 1
      },
      {
        "name": "Warstorm Surge",
        "count": 1
      },
      {
        "name": "Where Ancients Tread",
        "count": 1
      },
      {
        "name": "Witch Hunt",
        "count": 1
      },
      {
        "name": "Boros Garrison",
        "count": 1
      },
      {
        "name": "Boros Guildgate",
        "count": 1
      },
      {
        "name": "Command Tower",
        "count": 1
      },
      {
        "name": "Contested Cliffs",
        "count": 1
      },
      {
        "name": "Drifting Meadow",
        "count": 1
      },
      {
        "name": "Evolving Wilds",
        "count": 1
      },
      {
        "name": "Forest",
        "count": 8
      },
      {
        "name": "Forgotten Cave",
        "count": 1
      },
      {
        "name": "Gruul Guildgate",
        "count": 1
      },
      {
        "name": "Homeward Path",
        "count": 1
      },
      {
        "name": "Jungle Shrine",
        "count": 1
      },
      {
        "name": "Khalni Garden",
        "count": 1
      },
      {
        "name": "Mosswort Bridge",
        "count": 1
      },
      {
        "name": "Mountain",
        "count": 5
      },
      {
        "name": "Naya Panorama",
        "count": 1
      },
      {
        "name": "New Benalia",
        "count": 1
      },
      {
        "name": "Opal Palace",
        "count": 1
      },
      {
        "name": "Plains",
        "count": 4
      },
      {
        "name": "Rupture Spire",
        "count": 1
      },
      {
        "name": "Secluded Steppe",
        "count": 1
      },
      {
        "name": "Selesnya Guildgate",
        "count": 1
      },
      {
        "name": "Selesnya Sanctuary",
        "count": 1
      },
      {
        "name": "Slippery Karst",
        "count": 1
      },
      {
        "name": "Smoldering Crater",
        "count": 1
      },
      {
        "name": "Temple of the False God",
        "count": 1
      },
      {
        "name": "Tranquil Thicket",
        "count": 1
      },
      {
        "name": "Vitu-Ghazi, the City-Tree",
        "count": 1
      },
      {
        "name": "Vivid Crag",
        "count": 1
      }
    ]
  },
  {
    "name": "Power Hungry",
    "commander": "Prossh, Skyraider of Kher",
    "expansion": "Commander 2013",
    "cards": [
      {
        "name": "Brooding Saurian",
        "count": 1
      },
      {
        "name": "Capricious Efreet",
        "count": 1
      },
      {
        "name": "Charnelhoard Wurm",
        "count": 1
      },
      {
        "name": "Deathbringer Thoctar",
        "count": 1
      },
      {
        "name": "Deepfire Elemental",
        "count": 1
      },
      {
        "name": "Elvish Skysweeper",
        "count": 1
      },
      {
        "name": "Endless Cockroaches",
        "count": 1
      },
      {
        "name": "Endrek Sahr, Master Breeder",
        "count": 1
      },
      {
        "name": "Fell Shepherd",
        "count": 1
      },
      {
        "name": "Goblin Sharpshooter",
        "count": 1
      },
      {
        "name": "Golgari Guildmage",
        "count": 1
      },
      {
        "name": "Hooded Horror",
        "count": 1
      },
      {
        "name": "Hua Tuo, Honored Physician",
        "count": 1
      },
      {
        "name": "Hunted Troll",
        "count": 1
      },
      {
        "name": "Inferno Titan",
        "count": 1
      },
      {
        "name": "Jade Mage",
        "count": 1
      },
      {
        "name": "Ophiomancer",
        "count": 1
      },
      {
        "name": "Quagmire Druid",
        "count": 1
      },
      {
        "name": "Sakura-Tribe Elder",
        "count": 1
      },
      {
        "name": "Scarland Thrinax",
        "count": 1
      },
      {
        "name": "Sek'Kuar, Deathkeeper",
        "count": 1
      },
      {
        "name": "Shattergang Brothers",
        "count": 1
      },
      {
        "name": "Silklash Spider",
        "count": 1
      },
      {
        "name": "Sprouting Thrinax",
        "count": 1
      },
      {
        "name": "Stalking Vengeance",
        "count": 1
      },
      {
        "name": "Stronghold Assassin",
        "count": 1
      },
      {
        "name": "Terra Ravager",
        "count": 1
      },
      {
        "name": "Viscera Seer",
        "count": 1
      },
      {
        "name": "Walker of the Grove",
        "count": 1
      },
      {
        "name": "Wight of Precinct Six",
        "count": 1
      },
      {
        "name": "Dirge of Dread",
        "count": 1
      },
      {
        "name": "Mass Mutiny",
        "count": 1
      },
      {
        "name": "Restore",
        "count": 1
      },
      {
        "name": "Rough // Tumble",
        "count": 1
      },
      {
        "name": "Spoils of Victory",
        "count": 1
      },
      {
        "name": "Sudden Demise",
        "count": 1
      },
      {
        "name": "Tempt with Vengeance",
        "count": 1
      },
      {
        "name": "Jund Charm",
        "count": 1
      },
      {
        "name": "Reincarnation",
        "count": 1
      },
      {
        "name": "Armillary Sphere",
        "count": 1
      },
      {
        "name": "Carnage Altar",
        "count": 1
      },
      {
        "name": "Jar of Eyeballs",
        "count": 1
      },
      {
        "name": "Obelisk of Jund",
        "count": 1
      },
      {
        "name": "Plague Boiler",
        "count": 1
      },
      {
        "name": "Sol Ring",
        "count": 1
      },
      {
        "name": "Spine of Ish Sah",
        "count": 1
      },
      {
        "name": "Swiftfoot Boots",
        "count": 1
      },
      {
        "name": "Blood Rites",
        "count": 1
      },
      {
        "name": "Curse of Chaos",
        "count": 1
      },
      {
        "name": "Curse of Predation",
        "count": 1
      },
      {
        "name": "Curse of Shallow Graves",
        "count": 1
      },
      {
        "name": "Fecundity",
        "count": 1
      },
      {
        "name": "Foster",
        "count": 1
      },
      {
        "name": "Furnace Celebration",
        "count": 1
      },
      {
        "name": "Goblin Bombardment",
        "count": 1
      },
      {
        "name": "Night Soil",
        "count": 1
      },
      {
        "name": "Primal Vigor",
        "count": 1
      },
      {
        "name": "Tooth and Claw",
        "count": 1
      },
      {
        "name": "Vile Requiem",
        "count": 1
      },
      {
        "name": "Widespread Panic",
        "count": 1
      },
      {
        "name": "Akoum Refuge",
        "count": 1
      },
      {
        "name": "Command Tower",
        "count": 1
      },
      {
        "name": "Evolving Wilds",
        "count": 1
      },
      {
        "name": "Forest",
        "count": 7
      },
      {
        "name": "Golgari Guildgate",
        "count": 1
      },
      {
        "name": "Golgari Rot Farm",
        "count": 1
      },
      {
        "name": "Grim Backwoods",
        "count": 1
      },
      {
        "name": "Gruul Guildgate",
        "count": 1
      },
      {
        "name": "Jund Panorama",
        "count": 1
      },
      {
        "name": "Kazandu Refuge",
        "count": 1
      },
      {
        "name": "Khalni Garden",
        "count": 1
      },
      {
        "name": "Kher Keep",
        "count": 1
      },
      {
        "name": "Llanowar Reborn",
        "count": 1
      },
      {
        "name": "Mountain",
        "count": 7
      },
      {
        "name": "Opal Palace",
        "count": 1
      },
      {
        "name": "Rakdos Guildgate",
        "count": 1
      },
      {
        "name": "Rupture Spire",
        "count": 1
      },
      {
        "name": "Savage Lands",
        "count": 1
      },
      {
        "name": "Swamp",
        "count": 6
      },
      {
        "name": "Temple of the False God",
        "count": 1
      },
      {
        "name": "Terramorphic Expanse",
        "count": 1
      },
      {
        "name": "Vivid Grove",
        "count": 1
      }
    ]
  },
  {
    "name": "Built From Scratch",
    "commander": "Daretti, Scrap Savant",
    "expansion": "Commander 2014",
    "cards": [
      {
        "name": "Goblin Welder",
        "count": 1
      },
      {
        "name": "Epochrasite",
        "count": 1
      },
      {
        "name": "Myr Retriever",
        "count": 1
      },
      {
        "name": "Myr Sire",
        "count": 1
      },
      {
        "name": "Bottle Gnomes",
        "count": 1
      },
      {
        "name": "Cathodion",
        "count": 1
      },
      {
        "name": "Junk Diver",
        "count": 1
      },
      {
        "name": "Palladium Myr",
        "count": 1
      },
      {
        "name": "Pilgrim's Eye",
        "count": 1
      },
      {
        "name": "Tuktuk the Explorer",
        "count": 1
      },
      {
        "name": "Dualcaster Mage",
        "count": 1
      },
      {
        "name": "Feldon of the Third Path",
        "count": 1
      },
      {
        "name": "Solemn Simulacrum",
        "count": 1
      },
      {
        "name": "Flametongue Kavu",
        "count": 1
      },
      {
        "name": "Beetleback Chief",
        "count": 1
      },
      {
        "name": "Ingot Chewer",
        "count": 1
      },
      {
        "name": "Steel Hellkite",
        "count": 1
      },
      {
        "name": "Wurmcoil Engine",
        "count": 1
      },
      {
        "name": "Spitebellows",
        "count": 1
      },
      {
        "name": "Hoard-Smelter Dragon",
        "count": 1
      },
      {
        "name": "Warmonger Hellkite",
        "count": 1
      },
      {
        "name": "Myr Battlesphere",
        "count": 1
      },
      {
        "name": "Pentavus",
        "count": 1
      },
      {
        "name": "Tyrant's Familiar",
        "count": 1
      },
      {
        "name": "Bosh, Iron Golem",
        "count": 1
      },
      {
        "name": "Bogardan Hellkite",
        "count": 1
      },
      {
        "name": "Faithless Looting",
        "count": 1
      },
      {
        "name": "Whipflare",
        "count": 1
      },
      {
        "name": "Scrap Mastery",
        "count": 1
      },
      {
        "name": "Incite Rebellion",
        "count": 1
      },
      {
        "name": "Blasphemous Act",
        "count": 1
      },
      {
        "name": "Impact Resonance",
        "count": 1
      },
      {
        "name": "Chaos Warp",
        "count": 1
      },
      {
        "name": "Volcanic Offering",
        "count": 1
      },
      {
        "name": "Word of Seizing",
        "count": 1
      },
      {
        "name": "Magmaquake",
        "count": 1
      },
      {
        "name": "Starstorm",
        "count": 1
      },
      {
        "name": "Everflowing Chalice",
        "count": 1
      },
      {
        "name": "Panic Spellbomb",
        "count": 1
      },
      {
        "name": "Sol Ring",
        "count": 1
      },
      {
        "name": "Wayfarer's Bauble",
        "count": 1
      },
      {
        "name": "Fire Diamond",
        "count": 1
      },
      {
        "name": "Ichor Wellspring",
        "count": 1
      },
      {
        "name": "Liquimetal Coating",
        "count": 1
      },
      {
        "name": "Mind Stone",
        "count": 1
      },
      {
        "name": "Mycosynth Wellspring",
        "count": 1
      },
      {
        "name": "Ruby Medallion",
        "count": 1
      },
      {
        "name": "Swiftfoot Boots",
        "count": 1
      },
      {
        "name": "Commander's Sphere",
        "count": 1
      },
      {
        "name": "Jalum Tome",
        "count": 1
      },
      {
        "name": "Pristine Talisman",
        "count": 1
      },
      {
        "name": "Unstable Obelisk",
        "count": 1
      },
      {
        "name": "Trading Post",
        "count": 1
      },
      {
        "name": "Caged Sun",
        "count": 1
      },
      {
        "name": "Dreamstone Hedron",
        "count": 1
      },
      {
        "name": "Loreseeker's Stone",
        "count": 1
      },
      {
        "name": "Spine of Ish Sah",
        "count": 1
      },
      {
        "name": "Darksteel Citadel",
        "count": 1
      },
      {
        "name": "Great Furnace",
        "count": 1
      },
      {
        "name": "Bitter Feud",
        "count": 1
      },
      {
        "name": "Arcane Lighthouse",
        "count": 1
      },
      {
        "name": "Buried Ruin",
        "count": 1
      },
      {
        "name": "Dormant Volcano",
        "count": 1
      },
      {
        "name": "Flamekin Village",
        "count": 1
      },
      {
        "name": "Forgotten Cave",
        "count": 1
      },
      {
        "name": "Ghost Quarter",
        "count": 1
      },
      {
        "name": "Phyrexia's Core",
        "count": 1
      },
      {
        "name": "Reliquary Tower",
        "count": 1
      },
      {
        "name": "Smoldering Crater",
        "count": 1
      },
      {
        "name": "Temple of the False God",
        "count": 1
      },
      {
        "name": "Mountain",
        "count": 29
      }
    ]
  },
  {
    "name": "Forged In Stone",
    "commander": "Nahiri, the Lithomancer",
    "expansion": "Commander 2014",
    "cards": [
      {
        "name": "Containment Priest",
        "count": 1
      },
      {
        "name": "Whitemane Lion",
        "count": 1
      },
      {
        "name": "Grand Abolisher",
        "count": 1
      },
      {
        "name": "Kor Sanctifiers",
        "count": 1
      },
      {
        "name": "Mentor of the Meek",
        "count": 1
      },
      {
        "name": "Flickerwisp",
        "count": 1
      },
      {
        "name": "Hallowed Spiritkeeper",
        "count": 1
      },
      {
        "name": "Kemba, Kha Regent",
        "count": 1
      },
      {
        "name": "Silverblade Paladin",
        "count": 1
      },
      {
        "name": "Skyhunter Skirmisher",
        "count": 1
      },
      {
        "name": "Angelic Field Marshal",
        "count": 1
      },
      {
        "name": "Celestial Crusader",
        "count": 1
      },
      {
        "name": "Jazal Goldmane",
        "count": 1
      },
      {
        "name": "Geist-Honored Monk",
        "count": 1
      },
      {
        "name": "Requiem Angel",
        "count": 1
      },
      {
        "name": "Adarkar Valkyrie",
        "count": 1
      },
      {
        "name": "Sun Titan",
        "count": 1
      },
      {
        "name": "Sunblast Angel",
        "count": 1
      },
      {
        "name": "Twilight Shepherd",
        "count": 1
      },
      {
        "name": "Angel of the Dire Hour",
        "count": 1
      },
      {
        "name": "Serra Avatar",
        "count": 1
      },
      {
        "name": "Gift of Estates",
        "count": 1
      },
      {
        "name": "Spectral Procession",
        "count": 1
      },
      {
        "name": "Fell the Mighty",
        "count": 1
      },
      {
        "name": "Nomads' Assembly",
        "count": 1
      },
      {
        "name": "Deploy to the Front",
        "count": 1
      },
      {
        "name": "Martial Coup",
        "count": 1
      },
      {
        "name": "Decree of Justice",
        "count": 1
      },
      {
        "name": "Brave the Elements",
        "count": 1
      },
      {
        "name": "Condemn",
        "count": 1
      },
      {
        "name": "Afterlife",
        "count": 1
      },
      {
        "name": "Midnight Haunting",
        "count": 1
      },
      {
        "name": "Oblation",
        "count": 1
      },
      {
        "name": "Wing Shards",
        "count": 1
      },
      {
        "name": "Benevolent Offering",
        "count": 1
      },
      {
        "name": "Comeuppance",
        "count": 1
      },
      {
        "name": "Return to Dust",
        "count": 1
      },
      {
        "name": "White Sun's Zenith",
        "count": 1
      },
      {
        "name": "Masterwork of Ingenuity",
        "count": 1
      },
      {
        "name": "Skullclamp",
        "count": 1
      },
      {
        "name": "Sol Ring",
        "count": 1
      },
      {
        "name": "Marble Diamond",
        "count": 1
      },
      {
        "name": "Mask of Memory",
        "count": 1
      },
      {
        "name": "Pearl Medallion",
        "count": 1
      },
      {
        "name": "Swiftfoot Boots",
        "count": 1
      },
      {
        "name": "Commander's Sphere",
        "count": 1
      },
      {
        "name": "Loxodon Warhammer",
        "count": 1
      },
      {
        "name": "Strata Scythe",
        "count": 1
      },
      {
        "name": "Sword of Vengeance",
        "count": 1
      },
      {
        "name": "Assault Suit",
        "count": 1
      },
      {
        "name": "Bonehoard",
        "count": 1
      },
      {
        "name": "Moonsilver Spear",
        "count": 1
      },
      {
        "name": "Argentum Armor",
        "count": 1
      },
      {
        "name": "Loreseeker's Stone",
        "count": 1
      },
      {
        "name": "Armistice",
        "count": 1
      },
      {
        "name": "Mobilization",
        "count": 1
      },
      {
        "name": "Sacred Mesa",
        "count": 1
      },
      {
        "name": "Marshal's Anthem",
        "count": 1
      },
      {
        "name": "Cathars' Crusade",
        "count": 1
      },
      {
        "name": "True Conviction",
        "count": 1
      },
      {
        "name": "Arcane Lighthouse",
        "count": 1
      },
      {
        "name": "Drifting Meadow",
        "count": 1
      },
      {
        "name": "Emeria, the Sky Ruin",
        "count": 1
      },
      {
        "name": "Ghost Quarter",
        "count": 1
      },
      {
        "name": "Karoo",
        "count": 1
      },
      {
        "name": "Secluded Steppe",
        "count": 1
      },
      {
        "name": "Temple of the False God",
        "count": 1
      },
      {
        "name": "Plains",
        "count": 32
      }
    ]
  },
  {
    "name": "Guided By Nature",
    "commander": "Freyalise, Llanowar's Fury",
    "expansion": "Commander 2014",
    "cards": [
      {
        "name": "Elvish Mystic",
        "count": 1
      },
      {
        "name": "Elvish Skysweeper",
        "count": 1
      },
      {
        "name": "Essence Warden",
        "count": 1
      },
      {
        "name": "Joraga Warcaller",
        "count": 1
      },
      {
        "name": "Llanowar Elves",
        "count": 1
      },
      {
        "name": "Sylvan Safekeeper",
        "count": 1
      },
      {
        "name": "Elvish Visionary",
        "count": 1
      },
      {
        "name": "Priest of Titania",
        "count": 1
      },
      {
        "name": "Sylvan Ranger",
        "count": 1
      },
      {
        "name": "Thornweald Archer",
        "count": 1
      },
      {
        "name": "Wellwisher",
        "count": 1
      },
      {
        "name": "Farhaven Elf",
        "count": 1
      },
      {
        "name": "Imperious Perfect",
        "count": 1
      },
      {
        "name": "Reclamation Sage",
        "count": 1
      },
      {
        "name": "Timberwatch Elf",
        "count": 1
      },
      {
        "name": "Titania's Chosen",
        "count": 1
      },
      {
        "name": "Wood Elves",
        "count": 1
      },
      {
        "name": "Elvish Archdruid",
        "count": 1
      },
      {
        "name": "Ezuri, Renegade Leader",
        "count": 1
      },
      {
        "name": "Drove of Elves",
        "count": 1
      },
      {
        "name": "Immaculate Magistrate",
        "count": 1
      },
      {
        "name": "Wren's Run Packmaster",
        "count": 1
      },
      {
        "name": "Lys Alana Huntmaster",
        "count": 1
      },
      {
        "name": "Masked Admirers",
        "count": 1
      },
      {
        "name": "Wolfbriar Elemental",
        "count": 1
      },
      {
        "name": "Creeperhulk",
        "count": 1
      },
      {
        "name": "Silklash Spider",
        "count": 1
      },
      {
        "name": "Titania, Protector of Argoth",
        "count": 1
      },
      {
        "name": "Grave Sifter",
        "count": 1
      },
      {
        "name": "Primordial Sage",
        "count": 1
      },
      {
        "name": "Rampaging Baloths",
        "count": 1
      },
      {
        "name": "Soul of the Harvest",
        "count": 1
      },
      {
        "name": "Thunderfoot Baloth",
        "count": 1
      },
      {
        "name": "Siege Behemoth",
        "count": 1
      },
      {
        "name": "Tornado Elemental",
        "count": 1
      },
      {
        "name": "Terastodon",
        "count": 1
      },
      {
        "name": "Lifeblood Hydra",
        "count": 1
      },
      {
        "name": "Hunting Triad",
        "count": 1
      },
      {
        "name": "Whirlwind",
        "count": 1
      },
      {
        "name": "Overwhelming Stampede",
        "count": 1
      },
      {
        "name": "Overrun",
        "count": 1
      },
      {
        "name": "Grim Flowering",
        "count": 1
      },
      {
        "name": "Collective Unconscious",
        "count": 1
      },
      {
        "name": "Desert Twister",
        "count": 1
      },
      {
        "name": "Wave of Vitriol",
        "count": 1
      },
      {
        "name": "Praetor's Counsel",
        "count": 1
      },
      {
        "name": "Sylvan Offering",
        "count": 1
      },
      {
        "name": "Harrow",
        "count": 1
      },
      {
        "name": "Fresh Meat",
        "count": 1
      },
      {
        "name": "Skullclamp",
        "count": 1
      },
      {
        "name": "Sol Ring",
        "count": 1
      },
      {
        "name": "Emerald Medallion",
        "count": 1
      },
      {
        "name": "Moss Diamond",
        "count": 1
      },
      {
        "name": "Swiftfoot Boots",
        "count": 1
      },
      {
        "name": "Commander's Sphere",
        "count": 1
      },
      {
        "name": "Assault Suit",
        "count": 1
      },
      {
        "name": "Seer's Sundial",
        "count": 1
      },
      {
        "name": "Predator, Flagship",
        "count": 1
      },
      {
        "name": "Loreseeker's Stone",
        "count": 1
      },
      {
        "name": "Beastmaster Ascension",
        "count": 1
      },
      {
        "name": "Song of the Dryads",
        "count": 1
      },
      {
        "name": "Wolfcaller's Howl",
        "count": 1
      },
      {
        "name": "Crystal Vein",
        "count": 1
      },
      {
        "name": "Evolving Wilds",
        "count": 1
      },
      {
        "name": "Gargoyle Castle",
        "count": 1
      },
      {
        "name": "Ghost Quarter",
        "count": 1
      },
      {
        "name": "Haunted Fengraf",
        "count": 1
      },
      {
        "name": "Havenwood Battleground",
        "count": 1
      },
      {
        "name": "Jungle Basin",
        "count": 1
      },
      {
        "name": "Myriad Landscape",
        "count": 1
      },
      {
        "name": "Oran-Rief, the Vastwood",
        "count": 1
      },
      {
        "name": "Slippery Karst",
        "count": 1
      },
      {
        "name": "Terramorphic Expanse",
        "count": 1
      },
      {
        "name": "Tranquil Thicket",
        "count": 1
      },
      {
        "name": "Forest",
        "count": 25
      }
    ]
  }
]